god_like/__init__.py
god_like/godlike.py
god_like/request.py
god_like/response.py
god_like-1.0.1.dist-info/WHEEL
god_like-1.0.1.dist-info/METADATA
god_like-1.0.1.dist-info/RECORD
