Metadata-Version: 2.1
Name: god-like
Version: 1.0.1
Summary: Flask for humans.
Home-page: https://github.com/hostedposted/god-like/
License: MIT
Author: hostedposted
Author-email: hostedpostedsite@gmail.com
Requires-Python: >=3.8,<4.0
Classifier: License :: OSI Approved :: MIT License
Classifier: Programming Language :: Python :: 3
Classifier: Programming Language :: Python :: 3.8
Classifier: Programming Language :: Python :: 3.9
Requires-Dist: Flask (>=2.0.1,<3.0.0)
Requires-Dist: Werkzeug (>=2.0.1,<3.0.0)
Project-URL: Documentation, https://hostedposted.github.io/god-like/latest/
Project-URL: Repository, https://github.com/hostedposted/god-like/
